{
  "resourceTemplates": [
    {
      "uriTemplate": "https://graph.microsoft.com/beta/sites/{siteId}/lists/{listId}/items?$expand=fields($select=Title,ID,Created,Modified,Author,Editor)&$select=id,createdDateTime,lastModifiedDateTime",
      "name": "get-all-list-items",
      "title": "Get all list items",
      "description": "Returns all list items (rows) with just the core field values (Title, Created, etc.). No bloat.",
      "mimeType": "application/json",
      "annotations": {
        "audience": [
          "assistant"
        ]
      }
    },
    {
      "uriTemplate": "https://graph.microsoft.com/beta/sites/{siteId}/lists/{listId}/items/{itemId}?$expand=fields($select=Title,ID,Created,Modified,Author,Editor)&$select=id,createdDateTime,lastModifiedDateTime",
      "name": "get-list-item-details",
      "title": "Get list item details",
      "description": "Fetches a single list item with just the essentials: main fields, timestamps, and author/editor.",
      "mimeType": "application/json",
      "annotations": {
        "audience": [
          "assistant"
        ]
      }
    }
  ]
}